netbox_static_routes/__init__.py
netbox_static_routes/filtersets.py
netbox_static_routes/forms.py
netbox_static_routes/graphql.py
netbox_static_routes/models.py
netbox_static_routes/navigation.py
netbox_static_routes/tables.py
netbox_static_routes/urls.py
netbox_static_routes/version.py
netbox_static_routes/views.py
netbox_static_routes/api/__init__.py
netbox_static_routes/api/serializers.py
netbox_static_routes/api/urls.py
netbox_static_routes/api/views.py
netbox_static_routes/migrations/0001_initial.py
netbox_static_routes/migrations/__init__.py
netbox_static_routes/templates/netbox_static_routes/staticroute.html
netbox_static_routes_plugin-0.3.dist-info/LICENSE
netbox_static_routes_plugin-0.3.dist-info/METADATA
netbox_static_routes_plugin-0.3.dist-info/WHEEL
netbox_static_routes_plugin-0.3.dist-info/top_level.txt
netbox_static_routes_plugin-0.3.dist-info/RECORD
